Workbook

Sheet Supuestos
A1: Supuestos — las celdas amarillas son las únicas que se tocan
A2: Todo lo demás en este archivo son fórmulas que dependen de acá. Cambiá un amarillo y las proyecciones de 24 meses se recalculan solas. Las filas marcadas DATO no son opinión: salen del código del producto o de una medición.
A4: Concepto | B4: Valor | C4: Unidad | D4: Origen | E4: Qué pasa si te equivocás
A5: PRECIO Y PRODUCTO
A6: Precio Professional mensual | B6: 9 | C6: USD/mes | D6: DATO | E6: Es lo que cobra api/_planes.js. Cambiarlo acá NO cambia el checkout.
A7: Precio Professional anual | B7: 90 | C7: USD/año | D7: DATO | E7: 12 meses al precio de 10. También de api/_planes.js.
A8: Tipo de cambio USD→UYU | B8: 40 | C8: UYU/USD | D8: DATO | E8: El default de MP_TASA_UYU. Se cobra en pesos: si el peso se mueve, tu ingreso en USD se mueve.
A9: % de clientes que eligen el plan anual | B9: 0.3 | C9: proporción | D9: SUPUESTO | E9: Sube el ingreso del mes 1 y baja el recurrente. Si vendés más anual de lo previsto, entra más plata antes y menos después.
A10: VENTAS
A11: Clientes nuevos por mes (sin ads) | B11: 2 | C11: clientes/mes | D11: SUPUESTO | E11: El supuesto MÁS sensible de todo el modelo. Con 0 no hay negocio por más que el resto esté bien.
A12: Clientes nuevos por mes (con ads) | B12: 6 | C12: clientes/mes | D12: SUPUESTO | E12: Sólo vale si el costo por cliente de abajo es real. Poné el que midas, no el que quieras.
A13: Churn mensual | B13: 0.05 | C13: proporción | D13: SUPUESTO | E13: 5% mensual = perdés la mitad de tu base en 14 meses. Es el número que decide si esto crece o se estanca.
A14: COSTOS VARIABLES
A15: Comisión MercadoPago | B15: 0.0599 | C15: proporción | D15: SUPUESTO | E15: PONÉ EL TUYO. /api/metricas te da el real medido (neto que entró ÷ bruto cobrado). Varía por medio de pago y plazo de acreditación.
A16: Costo de IA por cliente activo | B16: 0.5 | C16: USD/mes | D16: SUPUESTO | E16: Cupo de 1000 consultas/mes en el plan Professional. El motor de reglas no gasta nada; esto es sólo el copiloto.
A17: Gasto en ads por mes | B17: 200 | C17: USD/mes | D17: SUPUESTO | E17: Escenario 'con ads'. El escenario 'sin ads' lo ignora.
A18: Costo de adquisición por cliente (CAC) | B18: 50 | C18: USD/cliente | D18: SUPUESTO | E18: Si CAC > lo que deja un cliente en toda su vida, cada venta te hace perder plata. La planilla lo calcula abajo.
A19: COSTOS FIJOS
A20: Dominio web | B20: 1.5 | C20: USD/mes | D20: OBLIGATORIO | E20: ~USD 15-20/año. Es el único gasto de plataforma inevitable.
A21: Hosting (Vercel) | B21: 0 | C21: USD/mes | D21: SUPUESTO | E21: El plan Hobby es gratis pero su licencia es para uso NO comercial. Vender por ahí exige Pro. Ver la hoja 'Plataformas'.
A22: Otros fijos (contador, etc.) | B22: 0 | C22: USD/mes | D22: SUPUESTO | E22: Un contador en Uruguay no es opcional si facturás. Poné lo que te cotice.
A23: IMPUESTOS (Uruguay)
A24: IVA sobre ventas locales | B24: 0.22 | C24: proporción | D24: TASA VIGENTE | E24: 22% es la tasa básica. Ojo: la exportación de servicios (cliente NO residente) tiene tratamiento distinto — ver hoja 'Impuestos UY'.
A25: % de ventas a clientes uruguayos | B25: 0.5 | C25: proporción | D25: SUPUESTO | E25: Lo que NO es local puede calificar como exportación de servicios. Cambia mucho la cuenta.
A26: IRAE sobre la ganancia | B26: 0.25 | C26: proporción | D26: TASA VIGENTE | E26: 25% sobre la renta neta fiscal en el régimen general.
A27: ¿Régimen simplificado? (1=sí, 0=no) | B27: 0 | C27: 1/0 | D27: SUPUESTO | E27: Con 1, el modelo ignora IRAE e IVA y usa el costo fijo de abajo. CONFIRMALO CON UN CONTADOR antes de usarlo.
A28: Costo fijo del régimen simplificado | B28: 0 | C28: USD/mes | D28: SUPUESTO | E28: Monotributo / Literal E: aporte fijo mensual. Poné el vigente.

Sheet Proyección sin ads
A1: Proyección sin ads — 24 meses
A2: Cada fila es un mes. Las columnas son fórmulas: no hay ningún número escrito a mano acá. Los meses 1, 3, 6, 9, 12, 18 y 24 están resaltados porque son los que pediste. 'Acumulado' es lo que te queda en el bolsillo desde el mes 1 — mientras sea negativo, estás poniendo plata.
A4: Mes | B4: Clientes activos | C4: Altas | D4: Bajas (churn) | E4: Ingreso bruto USD | F4: Comisión MP | G4: Costo IA | H4: Ads | I4: Fijos | J4: Impuestos | K4: Neto del mes | L4: Acumulado
A5: 1 | B5: =Supuestos!$B$11 | C5: =Supuestos!$B$11 | D5: =0 | E5: =C5*Supuestos!$B$9*Supuestos!$B$7+B5*(1-Supuestos!$B$9)*Supuestos!$B$6 | F5: =E5*Supuestos!$B$15 | G5: =B5*Supuestos!$B$16 | H5: =0 | I5: =Supuestos!$B$20+Supuestos!$B$21+Supuestos!$B$22 | J5: =IF(Supuestos!$B$27=1,Supuestos!$B$28,E5*Supuestos!$B$25*Supuestos!$B$24+MAX(0,(E5-F5-G5-H5-I5-E5*Supuestos!$B$25*Supuestos!$B$24))*Supuestos!$B$26) | K5: =E5-F5-G5-H5-I5-J5 | L5: =K5
A6: 2 | B6: =ROUND(B5*(1-Supuestos!$B$13)+Supuestos!$B$11,0) | C6: =Supuestos!$B$11 | D6: =ROUND(B5*Supuestos!$B$13,1) | E6: =C6*Supuestos!$B$9*Supuestos!$B$7+B6*(1-Supuestos!$B$9)*Supuestos!$B$6 | F6: =E6*Supuestos!$B$15 | G6: =B6*Supuestos!$B$16 | H6: =0 | I6: =Supuestos!$B$20+Supuestos!$B$21+Supuestos!$B$22 | J6: =IF(Supuestos!$B$27=1,Supuestos!$B$28,E6*Supuestos!$B$25*Supuestos!$B$24+MAX(0,(E6-F6-G6-H6-I6-E6*Supuestos!$B$25*Supuestos!$B$24))*Supuestos!$B$26) | K6: =E6-F6-G6-H6-I6-J6 | L6: =L5+K6
A7: 3 | B7: =ROUND(B6*(1-Supuestos!$B$13)+Supuestos!$B$11,0) | C7: =Supuestos!$B$11 | D7: =ROUND(B6*Supuestos!$B$13,1) | E7: =C7*Supuestos!$B$9*Supuestos!$B$7+B7*(1-Supuestos!$B$9)*Supuestos!$B$6 | F7: =E7*Supuestos!$B$15 | G7: =B7*Supuestos!$B$16 | H7: =0 | I7: =Supuestos!$B$20+Supuestos!$B$21+Supuestos!$B$22 | J7: =IF(Supuestos!$B$27=1,Supuestos!$B$28,E7*Supuestos!$B$25*Supuestos!$B$24+MAX(0,(E7-F7-G7-H7-I7-E7*Supuestos!$B$25*Supuestos!$B$24))*Supuestos!$B$26) | K7: =E7-F7-G7-H7-I7-J7 | L7: =L6+K7
A8: 4 | B8: =ROUND(B7*(1-Supuestos!$B$13)+Supuestos!$B$11,0) | C8: =Supuestos!$B$11 | D8: =ROUND(B7*Supuestos!$B$13,1) | E8: =C8*Supuestos!$B$9*Supuestos!$B$7+B8*(1-Supuestos!$B$9)*Supuestos!$B$6 | F8: =E8*Supuestos!$B$15 | G8: =B8*Supuestos!$B$16 | H8: =0 | I8: =Supuestos!$B$20+Supuestos!$B$21+Supuestos!$B$22 | J8: =IF(Supuestos!$B$27=1,Supuestos!$B$28,E8*Supuestos!$B$25*Supuestos!$B$24+MAX(0,(E8-F8-G8-H8-I8-E8*Supuestos!$B$25*Supuestos!$B$24))*Supuestos!$B$26) | K8: =E8-F8-G8-H8-I8-J8 | L8: =L7+K8
A9: 5 | B9: =ROUND(B8*(1-Supuestos!$B$13)+Supuestos!$B$11,0) | C9: =Supuestos!$B$11 | D9: =ROUND(B8*Supuestos!$B$13,1) | E9: =C9*Supuestos!$B$9*Supuestos!$B$7+B9*(1-Supuestos!$B$9)*Supuestos!$B$6 | F9: =E9*Supuestos!$B$15 | G9: =B9*Supuestos!$B$16 | H9: =0 | I9: =Supuestos!$B$20+Supuestos!$B$21+Supuestos!$B$22 | J9: =IF(Supuestos!$B$27=1,Supuestos!$B$28,E9*Supuestos!$B$25*Supuestos!$B$24+MAX(0,(E9-F9-G9-H9-I9-E9*Supuestos!$B$25*Supuestos!$B$24))*Supuestos!$B$26) | K9: =E9-F9-G9-H9-I9-J9 | L9: =L8+K9
A10: 6 | B10: =ROUND(B9*(1-Supuestos!$B$13)+Supuestos!$B$11,0) | C10: =Supuestos!$B$11 | D10: =ROUND(B9*Supuestos!$B$13,1) | E10: =C10*Supuestos!$B$9*Supuestos!$B$7+B10*(1-Supuestos!$B$9)*Supuestos!$B$6 | F10: =E10*Supuestos!$B$15 | G10: =B10*Supuestos!$B$16 | H10: =0 | I10: =Supuestos!$B$20+Supuestos!$B$21+Supuestos!$B$22 | J10: =IF(Supuestos!$B$27=1,Supuestos!$B$28,E10*Supuestos!$B$25*Supuestos!$B$24+MAX(0,(E10-F10-G10-H10-I10-E10*Supuestos!$B$25*Supuestos!$B$24))*Supuestos!$B$26) | K10: =E10-F10-G10-H10-I10-J10 | L10: =L9+K10
A11: 7 | B11: =ROUND(B10*(1-Supuestos!$B$13)+Supuestos!$B$11,0) | C11: =Supuestos!$B$11 | D11: =ROUND(B10*Supuestos!$B$13,1) | E11: =C11*Supuestos!$B$9*Supuestos!$B$7+B11*(1-Supuestos!$B$9)*Supuestos!$B$6 | F11: =E11*Supuestos!$B$15 | G11: =B11*Supuestos!$B$16 | H11: =0 | I11: =Supuestos!$B$20+Supuestos!$B$21+Supuestos!$B$22 | J11: =IF(Supuestos!$B$27=1,Supuestos!$B$28,E11*Supuestos!$B$25*Supuestos!$B$24+MAX(0,(E11-F11-G11-H11-I11-E11*Supuestos!$B$25*Supuestos!$B$24))*Supuestos!$B$26) | K11: =E11-F11-G11-H11-I11-J11 | L11: =L10+K11
A12: 8 | B12: =ROUND(B11*(1-Supuestos!$B$13)+Supuestos!$B$11,0) | C12: =Supuestos!$B$11 | D12: =ROUND(B11*Supuestos!$B$13,1) | E12: =C12*Supuestos!$B$9*Supuestos!$B$7+B12*(1-Supuestos!$B$9)*Supuestos!$B$6 | F12: =E12*Supuestos!$B$15 | G12: =B12*Supuestos!$B$16 | H12: =0 | I12: =Supuestos!$B$20+Supuestos!$B$21+Supuestos!$B$22 | J12: =IF(Supuestos!$B$27=1,Supuestos!$B$28,E12*Supuestos!$B$25*Supuestos!$B$24+MAX(0,(E12-F12-G12-H12-I12-E12*Supuestos!$B$25*Supuestos!$B$24))*Supuestos!$B$26) | K12: =E12-F12-G12-H12-I12-J12 | L12: =L11+K12
A13: 9 | B13: =ROUND(B12*(1-Supuestos!$B$13)+Supuestos!$B$11,0) | C13: =Supuestos!$B$11 | D13: =ROUND(B12*Supuestos!$B$13,1) | E13: =C13*Supuestos!$B$9*Supuestos!$B$7+B13*(1-Supuestos!$B$9)*Supuestos!$B$6 | F13: =E13*Supuestos!$B$15 | G13: =B13*Supuestos!$B$16 | H13: =0 | I13: =Supuestos!$B$20+Supuestos!$B$21+Supuestos!$B$22 | J13: =IF(Supuestos!$B$27=1,Supuestos!$B$28,E13*Supuestos!$B$25*Supuestos!$B$24+MAX(0,(E13-F13-G13-H13-I13-E13*Supuestos!$B$25*Supuestos!$B$24))*Supuestos!$B$26) | K13: =E13-F13-G13-H13-I13-J13 | L13: =L12+K13
A14: 10 | B14: =ROUND(B13*(1-Supuestos!$B$13)+Supuestos!$B$11,0) | C14: =Supuestos!$B$11 | D14: =ROUND(B13*Supuestos!$B$13,1) | E14: =C14*Supuestos!$B$9*Supuestos!$B$7+B14*(1-Supuestos!$B$9)*Supuestos!$B$6 | F14: =E14*Supuestos!$B$15 | G14: =B14*Supuestos!$B$16 | H14: =0 | I14: =Supuestos!$B$20+Supuestos!$B$21+Supuestos!$B$22 | J14: =IF(Supuestos!$B$27=1,Supuestos!$B$28,E14*Supuestos!$B$25*Supuestos!$B$24+MAX(0,(E14-F14-G14-H14-I14-E14*Supuestos!$B$25*Supuestos!$B$24))*Supuestos!$B$26) | K14: =E14-F14-G14-H14-I14-J14 | L14: =L13+K14
A15: 11 | B15: =ROUND(B14*(1-Supuestos!$B$13)+Supuestos!$B$11,0) | C15: =Supuestos!$B$11 | D15: =ROUND(B14*Supuestos!$B$13,1) | E15: =C15*Supuestos!$B$9*Supuestos!$B$7+B15*(1-Supuestos!$B$9)*Supuestos!$B$6 | F15: =E15*Supuestos!$B$15 | G15: =B15*Supuestos!$B$16 | H15: =0 | I15: =Supuestos!$B$20+Supuestos!$B$21+Supuestos!$B$22 | J15: =IF(Supuestos!$B$27=1,Supuestos!$B$28,E15*Supuestos!$B$25*Supuestos!$B$24+MAX(0,(E15-F15-G15-H15-I15-E15*Supuestos!$B$25*Supuestos!$B$24))*Supuestos!$B$26) | K15: =E15-F15-G15-H15-I15-J15 | L15: =L14+K15
A16: 12 | B16: =ROUND(B15*(1-Supuestos!$B$13)+Supuestos!$B$11,0) | C16: =Supuestos!$B$11 | D16: =ROUND(B15*Supuestos!$B$13,1) | E16: =C16*Supuestos!$B$9*Supuestos!$B$7+B16*(1-Supuestos!$B$9)*Supuestos!$B$6 | F16: =E16*Supuestos!$B$15 | G16: =B16*Supuestos!$B$16 | H16: =0 | I16: =Supuestos!$B$20+Supuestos!$B$21+Supuestos!$B$22 | J16: =IF(Supuestos!$B$27=1,Supuestos!$B$28,E16*Supuestos!$B$25*Supuestos!$B$24+MAX(0,(E16-F16-G16-H16-I16-E16*Supuestos!$B$25*Supuestos!$B$24))*Supuestos!$B$26) | K16: =E16-F16-G16-H16-I16-J16 | L16: =L15+K16
A17: 13 | B17: =ROUND(B16*(1-Supuestos!$B$13)+Supuestos!$B$11,0) | C17: =Supuestos!$B$11 | D17: =ROUND(B16*Supuestos!$B$13,1) | E17: =C17*Supuestos!$B$9*Supuestos!$B$7+B17*(1-Supuestos!$B$9)*Supuestos!$B$6 | F17: =E17*Supuestos!$B$15 | G17: =B17*Supuestos!$B$16 | H17: =0 | I17: =Supuestos!$B$20+Supuestos!$B$21+Supuestos!$B$22 | J17: =IF(Supuestos!$B$27=1,Supuestos!$B$28,E17*Supuestos!$B$25*Supuestos!$B$24+MAX(0,(E17-F17-G17-H17-I17-E17*Supuestos!$B$25*Supuestos!$B$24))*Supuestos!$B$26) | K17: =E17-F17-G17-H17-I17-J17 | L17: =L16+K17
... A28: 24 | B28: =ROUND(B27*(1-Supuestos!$B$13)+Supuestos!$B$11,0) | C28: =Supuestos!$B$11 | D28: =ROUND(B27*Supuestos!$B$13,1) | E28: =C28*Supuestos!$B$9*Supuestos!$B$7+B28*(1-Supuestos!$B$9)*Supuestos!$B$6 | F28: =E28*Supuestos!$B$15 | G28: =B28*Supuestos!$B$16 | H28: =0 | I28: =Supuestos!$B$20+Supuestos!$B$21+Supuestos!$B$22 | J28: =IF(Supuestos!$B$27=1,Supuestos!$B$28,E28*Supuestos!$B$25*Supuestos!$B$24+MAX(0,(E28-F28-G28-H28-I28-E28*Supuestos!$B$25*Supuestos!$B$24))*Supuestos!$B$26) | K28: =E28-F28-G28-H28-I28-J28 | L28: =L27+K28
A30: Mes en que el acumulado se vuelve positivo: | D30: =IFERROR(MATCH(TRUE,INDEX(L5:L28>0,0),0),"no en 24 meses")
A31: Valor de un cliente en toda su vida (LTV): | D31: =(Supuestos!$B$6*(1-Supuestos!$B$15)-Supuestos!$B$16)/Supuestos!$B$13

Sheet Proyección con ads
A1: Proyección con ads — 24 meses
A2: Cada fila es un mes. Las columnas son fórmulas: no hay ningún número escrito a mano acá. Los meses 1, 3, 6, 9, 12, 18 y 24 están resaltados porque son los que pediste. 'Acumulado' es lo que te queda en el bolsillo desde el mes 1 — mientras sea negativo, estás poniendo plata.
A4: Mes | B4: Clientes activos | C4: Altas | D4: Bajas (churn) | E4: Ingreso bruto USD | F4: Comisión MP | G4: Costo IA | H4: Ads | I4: Fijos | J4: Impuestos | K4: Neto del mes | L4: Acumulado
A5: 1 | B5: =Supuestos!$B$12 | C5: =Supuestos!$B$12 | D5: =0 | E5: =C5*Supuestos!$B$9*Supuestos!$B$7+B5*(1-Supuestos!$B$9)*Supuestos!$B$6 | F5: =E5*Supuestos!$B$15 | G5: =B5*Supuestos!$B$16 | H5: =Supuestos!$B$17 | I5: =Supuestos!$B$20+Supuestos!$B$21+Supuestos!$B$22 | J5: =IF(Supuestos!$B$27=1,Supuestos!$B$28,E5*Supuestos!$B$25*Supuestos!$B$24+MAX(0,(E5-F5-G5-H5-I5-E5*Supuestos!$B$25*Supuestos!$B$24))*Supuestos!$B$26) | K5: =E5-F5-G5-H5-I5-J5 | L5: =K5
A6: 2 | B6: =ROUND(B5*(1-Supuestos!$B$13)+Supuestos!$B$12,0) | C6: =Supuestos!$B$12 | D6: =ROUND(B5*Supuestos!$B$13,1) | E6: =C6*Supuestos!$B$9*Supuestos!$B$7+B6*(1-Supuestos!$B$9)*Supuestos!$B$6 | F6: =E6*Supuestos!$B$15 | G6: =B6*Supuestos!$B$16 | H6: =Supuestos!$B$17 | I6: =Supuestos!$B$20+Supuestos!$B$21+Supuestos!$B$22 | J6: =IF(Supuestos!$B$27=1,Supuestos!$B$28,E6*Supuestos!$B$25*Supuestos!$B$24+MAX(0,(E6-F6-G6-H6-I6-E6*Supuestos!$B$25*Supuestos!$B$24))*Supuestos!$B$26) | K6: =E6-F6-G6-H6-I6-J6 | L6: =L5+K6
A7: 3 | B7: =ROUND(B6*(1-Supuestos!$B$13)+Supuestos!$B$12,0) | C7: =Supuestos!$B$12 | D7: =ROUND(B6*Supuestos!$B$13,1) | E7: =C7*Supuestos!$B$9*Supuestos!$B$7+B7*(1-Supuestos!$B$9)*Supuestos!$B$6 | F7: =E7*Supuestos!$B$15 | G7: =B7*Supuestos!$B$16 | H7: =Supuestos!$B$17 | I7: =Supuestos!$B$20+Supuestos!$B$21+Supuestos!$B$22 | J7: =IF(Supuestos!$B$27=1,Supuestos!$B$28,E7*Supuestos!$B$25*Supuestos!$B$24+MAX(0,(E7-F7-G7-H7-I7-E7*Supuestos!$B$25*Supuestos!$B$24))*Supuestos!$B$26) | K7: =E7-F7-G7-H7-I7-J7 | L7: =L6+K7
A8: 4 | B8: =ROUND(B7*(1-Supuestos!$B$13)+Supuestos!$B$12,0) | C8: =Supuestos!$B$12 | D8: =ROUND(B7*Supuestos!$B$13,1) | E8: =C8*Supuestos!$B$9*Supuestos!$B$7+B8*(1-Supuestos!$B$9)*Supuestos!$B$6 | F8: =E8*Supuestos!$B$15 | G8: =B8*Supuestos!$B$16 | H8: =Supuestos!$B$17 | I8: =Supuestos!$B$20+Supuestos!$B$21+Supuestos!$B$22 | J8: =IF(Supuestos!$B$27=1,Supuestos!$B$28,E8*Supuestos!$B$25*Supuestos!$B$24+MAX(0,(E8-F8-G8-H8-I8-E8*Supuestos!$B$25*Supuestos!$B$24))*Supuestos!$B$26) | K8: =E8-F8-G8-H8-I8-J8 | L8: =L7+K8
A9: 5 | B9: =ROUND(B8*(1-Supuestos!$B$13)+Supuestos!$B$12,0) | C9: =Supuestos!$B$12 | D9: =ROUND(B8*Supuestos!$B$13,1) | E9: =C9*Supuestos!$B$9*Supuestos!$B$7+B9*(1-Supuestos!$B$9)*Supuestos!$B$6 | F9: =E9*Supuestos!$B$15 | G9: =B9*Supuestos!$B$16 | H9: =Supuestos!$B$17 | I9: =Supuestos!$B$20+Supuestos!$B$21+Supuestos!$B$22 | J9: =IF(Supuestos!$B$27=1,Supuestos!$B$28,E9*Supuestos!$B$25*Supuestos!$B$24+MAX(0,(E9-F9-G9-H9-I9-E9*Supuestos!$B$25*Supuestos!$B$24))*Supuestos!$B$26) | K9: =E9-F9-G9-H9-I9-J9 | L9: =L8+K9
A10: 6 | B10: =ROUND(B9*(1-Supuestos!$B$13)+Supuestos!$B$12,0) | C10: =Supuestos!$B$12 | D10: =ROUND(B9*Supuestos!$B$13,1) | E10: =C10*Supuestos!$B$9*Supuestos!$B$7+B10*(1-Supuestos!$B$9)*Supuestos!$B$6 | F10: =E10*Supuestos!$B$15 | G10: =B10*Supuestos!$B$16 | H10: =Supuestos!$B$17 | I10: =Supuestos!$B$20+Supuestos!$B$21+Supuestos!$B$22 | J10: =IF(Supuestos!$B$27=1,Supuestos!$B$28,E10*Supuestos!$B$25*Supuestos!$B$24+MAX(0,(E10-F10-G10-H10-I10-E10*Supuestos!$B$25*Supuestos!$B$24))*Supuestos!$B$26) | K10: =E10-F10-G10-H10-I10-J10 | L10: =L9+K10
A11: 7 | B11: =ROUND(B10*(1-Supuestos!$B$13)+Supuestos!$B$12,0) | C11: =Supuestos!$B$12 | D11: =ROUND(B10*Supuestos!$B$13,1) | E11: =C11*Supuestos!$B$9*Supuestos!$B$7+B11*(1-Supuestos!$B$9)*Supuestos!$B$6 | F11: =E11*Supuestos!$B$15 | G11: =B11*Supuestos!$B$16 | H11: =Supuestos!$B$17 | I11: =Supuestos!$B$20+Supuestos!$B$21+Supuestos!$B$22 | J11: =IF(Supuestos!$B$27=1,Supuestos!$B$28,E11*Supuestos!$B$25*Supuestos!$B$24+MAX(0,(E11-F11-G11-H11-I11-E11*Supuestos!$B$25*Supuestos!$B$24))*Supuestos!$B$26) | K11: =E11-F11-G11-H11-I11-J11 | L11: =L10+K11
A12: 8 | B12: =ROUND(B11*(1-Supuestos!$B$13)+Supuestos!$B$12,0) | C12: =Supuestos!$B$12 | D12: =ROUND(B11*Supuestos!$B$13,1) | E12: =C12*Supuestos!$B$9*Supuestos!$B$7+B12*(1-Supuestos!$B$9)*Supuestos!$B$6 | F12: =E12*Supuestos!$B$15 | G12: =B12*Supuestos!$B$16 | H12: =Supuestos!$B$17 | I12: =Supuestos!$B$20+Supuestos!$B$21+Supuestos!$B$22 | J12: =IF(Supuestos!$B$27=1,Supuestos!$B$28,E12*Supuestos!$B$25*Supuestos!$B$24+MAX(0,(E12-F12-G12-H12-I12-E12*Supuestos!$B$25*Supuestos!$B$24))*Supuestos!$B$26) | K12: =E12-F12-G12-H12-I12-J12 | L12: =L11+K12
A13: 9 | B13: =ROUND(B12*(1-Supuestos!$B$13)+Supuestos!$B$12,0) | C13: =Supuestos!$B$12 | D13: =ROUND(B12*Supuestos!$B$13,1) | E13: =C13*Supuestos!$B$9*Supuestos!$B$7+B13*(1-Supuestos!$B$9)*Supuestos!$B$6 | F13: =E13*Supuestos!$B$15 | G13: =B13*Supuestos!$B$16 | H13: =Supuestos!$B$17 | I13: =Supuestos!$B$20+Supuestos!$B$21+Supuestos!$B$22 | J13: =IF(Supuestos!$B$27=1,Supuestos!$B$28,E13*Supuestos!$B$25*Supuestos!$B$24+MAX(0,(E13-F13-G13-H13-I13-E13*Supuestos!$B$25*Supuestos!$B$24))*Supuestos!$B$26) | K13: =E13-F13-G13-H13-I13-J13 | L13: =L12+K13
A14: 10 | B14: =ROUND(B13*(1-Supuestos!$B$13)+Supuestos!$B$12,0) | C14: =Supuestos!$B$12 | D14: =ROUND(B13*Supuestos!$B$13,1) | E14: =C14*Supuestos!$B$9*Supuestos!$B$7+B14*(1-Supuestos!$B$9)*Supuestos!$B$6 | F14: =E14*Supuestos!$B$15 | G14: =B14*Supuestos!$B$16 | H14: =Supuestos!$B$17 | I14: =Supuestos!$B$20+Supuestos!$B$21+Supuestos!$B$22 | J14: =IF(Supuestos!$B$27=1,Supuestos!$B$28,E14*Supuestos!$B$25*Supuestos!$B$24+MAX(0,(E14-F14-G14-H14-I14-E14*Supuestos!$B$25*Supuestos!$B$24))*Supuestos!$B$26) | K14: =E14-F14-G14-H14-I14-J14 | L14: =L13+K14
A15: 11 | B15: =ROUND(B14*(1-Supuestos!$B$13)+Supuestos!$B$12,0) | C15: =Supuestos!$B$12 | D15: =ROUND(B14*Supuestos!$B$13,1) | E15: =C15*Supuestos!$B$9*Supuestos!$B$7+B15*(1-Supuestos!$B$9)*Supuestos!$B$6 | F15: =E15*Supuestos!$B$15 | G15: =B15*Supuestos!$B$16 | H15: =Supuestos!$B$17 | I15: =Supuestos!$B$20+Supuestos!$B$21+Supuestos!$B$22 | J15: =IF(Supuestos!$B$27=1,Supuestos!$B$28,E15*Supuestos!$B$25*Supuestos!$B$24+MAX(0,(E15-F15-G15-H15-I15-E15*Supuestos!$B$25*Supuestos!$B$24))*Supuestos!$B$26) | K15: =E15-F15-G15-H15-I15-J15 | L15: =L14+K15
A16: 12 | B16: =ROUND(B15*(1-Supuestos!$B$13)+Supuestos!$B$12,0) | C16: =Supuestos!$B$12 | D16: =ROUND(B15*Supuestos!$B$13,1) | E16: =C16*Supuestos!$B$9*Supuestos!$B$7+B16*(1-Supuestos!$B$9)*Supuestos!$B$6 | F16: =E16*Supuestos!$B$15 | G16: =B16*Supuestos!$B$16 | H16: =Supuestos!$B$17 | I16: =Supuestos!$B$20+Supuestos!$B$21+Supuestos!$B$22 | J16: =IF(Supuestos!$B$27=1,Supuestos!$B$28,E16*Supuestos!$B$25*Supuestos!$B$24+MAX(0,(E16-F16-G16-H16-I16-E16*Supuestos!$B$25*Supuestos!$B$24))*Supuestos!$B$26) | K16: =E16-F16-G16-H16-I16-J16 | L16: =L15+K16
A17: 13 | B17: =ROUND(B16*(1-Supuestos!$B$13)+Supuestos!$B$12,0) | C17: =Supuestos!$B$12 | D17: =ROUND(B16*Supuestos!$B$13,1) | E17: =C17*Supuestos!$B$9*Supuestos!$B$7+B17*(1-Supuestos!$B$9)*Supuestos!$B$6 | F17: =E17*Supuestos!$B$15 | G17: =B17*Supuestos!$B$16 | H17: =Supuestos!$B$17 | I17: =Supuestos!$B$20+Supuestos!$B$21+Supuestos!$B$22 | J17: =IF(Supuestos!$B$27=1,Supuestos!$B$28,E17*Supuestos!$B$25*Supuestos!$B$24+MAX(0,(E17-F17-G17-H17-I17-E17*Supuestos!$B$25*Supuestos!$B$24))*Supuestos!$B$26) | K17: =E17-F17-G17-H17-I17-J17 | L17: =L16+K17
... A28: 24 | B28: =ROUND(B27*(1-Supuestos!$B$13)+Supuestos!$B$12,0) | C28: =Supuestos!$B$12 | D28: =ROUND(B27*Supuestos!$B$13,1) | E28: =C28*Supuestos!$B$9*Supuestos!$B$7+B28*(1-Supuestos!$B$9)*Supuestos!$B$6 | F28: =E28*Supuestos!$B$15 | G28: =B28*Supuestos!$B$16 | H28: =Supuestos!$B$17 | I28: =Supuestos!$B$20+Supuestos!$B$21+Supuestos!$B$22 | J28: =IF(Supuestos!$B$27=1,Supuestos!$B$28,E28*Supuestos!$B$25*Supuestos!$B$24+MAX(0,(E28-F28-G28-H28-I28-E28*Supuestos!$B$25*Supuestos!$B$24))*Supuestos!$B$26) | K28: =E28-F28-G28-H28-I28-J28 | L28: =L27+K28
A30: Mes en que el acumulado se vuelve positivo: | D30: =IFERROR(MATCH(TRUE,INDEX(L5:L28>0,0),0),"no en 24 meses")
A31: Valor de un cliente en toda su vida (LTV): | D31: =(Supuestos!$B$6*(1-Supuestos!$B$15)-Supuestos!$B$16)/Supuestos!$B$13
A32: ¿El CAC se paga? (LTV − CAC): | D32: =D31-Supuestos!$B$18 | E32: Si esto da negativo, cada peso de ads te hace perder plata: no escales, arreglá el precio o el churn primero.

Sheet Impuestos UY
A1: Impuestos en Uruguay — estructura, no asesoramiento
A2: Esto ordena las preguntas que le tenés que hacer a un contador; no las responde. Las tasas son las generales y son estables. Lo que NO está acá son los topes de facturación de cada régimen, que se fijan en Unidades Indexadas y se actualizan todos los años: poner un número hoy sería darte un dato que vence. Preguntalo y anotalo.
A4: Tema | B4: Qué aplica | C4: Por qué te importa acá | D4: Qué preguntar
A5: IVA — venta local | B5: Tasa básica 22% | C5: Si le vendés a una empresa uruguaya, la venta lleva IVA. No es tuyo: lo cobrás y lo volcás. | D5: ¿Tengo que emitir e-factura desde la primera venta? ¿Qué software de facturación electrónica me sirve?
A6: IVA — exportación de servicios | B6: Tratamiento distinto al local | C6: Un cliente en Argentina, México o España puede no llevar IVA. Con mitad de tus ventas afuera, esto cambia el resultado más que cualquier otra línea de la planilla. | D6: Mi caso (software vendido online a no residentes) ¿califica como exportación de servicios? ¿Qué necesito documentar para probarlo?
A7: IRAE | B7: 25% sobre la renta neta fiscal | C7: Se paga sobre la GANANCIA, no sobre la venta. Los meses en rojo no pagan IRAE — la planilla ya lo contempla con un MAX(0;...). | D7: ¿Puedo deducir el gasto en ads, el hosting y mis horas? ¿Hay anticipos mensuales?
A8: Regímenes simplificados | B8: Monotributo · IRAE Literal E | C8: Para volumen chico pueden salir bastante más baratos que el régimen general. Tienen tope de facturación: el día que lo pasás, cambiás de régimen y la cuenta se rehace entera. | D8: ¿Cuál me corresponde hoy? ¿Cuál es el tope vigente? ¿Qué pasa el mes que lo supero?
A9: BPS | B9: Aportes personales | C9: Si facturás como unipersonal, aportás igual que cualquier independiente. Es un costo fijo mensual que existe aunque no vendas nada. | D9: ¿Cuánto aporto por mes en mi situación, vendiendo o no?
A10: Retenciones del exterior | B10: Varía por país del cliente | C10: Algunos países retienen impuesto en origen sobre pagos al exterior. Cobrás menos de lo facturado y no es culpa de MercadoPago. | D10: ¿Uruguay tiene convenio para evitar doble imposición con los países donde voy a vender?
A12: No soy contador y esto no es asesoramiento fiscal. Las tasas generales (IVA 22%, IRAE 25%) son públicas y estables; el régimen que te conviene, los topes vigentes y si tu venta califica como exportación de servicios dependen de tu situación concreta y cambian. Una consulta con un contador uruguayo cuesta mucho menos que elegir mal el régimen el primer año.

Sheet Plataformas
A1: Qué es obligatorio pagar y qué no
A2: Pediste no pagar nada salvo el dominio. Se puede casi entero. Las dos excepciones están marcadas en rojo y las dos son de licencia, no de capacidad técnica: el plan gratis alcanza de sobra para el volumen, pero su contrato no permite usarlo para vender.
A4: Plataforma | B4: Para qué se usa acá | C4: Plan gratis | D4: ¿Obligatorio pagar? | E4: Detalle
A5: Dominio web | B5: La dirección de la landing | C5: No existe gratis | D5: SÍ — el único | E5: ~USD 15-20/año según extensión. Es el gasto que aceptaste.
A6: Vercel | B6: Landing + funciones de pago + Blob | C6: Hobby: sí, y sobra para el volumen | D6: SÍ, por licencia | E6: El plan Hobby es para uso NO COMERCIAL. Un sitio que cobra es comercial. Técnicamente andaría; el problema es el contrato, y el riesgo es que te suspendan la cuenta justo cuando estás vendiendo. Verificá los términos vigentes antes de decidir.
A7: GitHub | B7: Código, CI y compilación de instaladores | C7: Sí. Repo público: Actions ilimitado. Privado: 2.000 min/mes | D7: NO (con una salvedad) | E7: Los runners de Windows consumen el DOBLE de minutos. Tres builds de instalador por push a main. Con el repo privado eso come cuota rápido — por eso los workflows ya tienen `concurrency` para no compilar dos veces lo mismo.
A8: MercadoPago | B8: Cobrar | C8: Sin costo fijo | D8: NO, pero cobra comisión | E8: No pagás mensualidad: se queda un porcentaje de cada venta. El real lo medís en /api/metricas y lo ponés en Supuestos.
A9: Vercel Blob | B9: Instalador descargable, canjes, descargas | C9: Sí, dentro del plan | D9: NO | E9: Ya está en el código. Falta el token: sin él, /api/download-installer responde 503 y el botón de la landing no baja nada.
A10: Claude / OpenAI / Gemini | B10: El copiloto con IA (opcional) | C10: Hay créditos iniciales | D10: NO | E10: El motor de reglas funciona sin ninguna clave. La IA es aditiva: si no hay clave configurada, el producto anda igual.
A11: Certificado SSL | B11: https | C11: Sí, incluido en Vercel | D11: NO | E11: Automático. No hay que hacer nada.

Sheet Competencia
A1: Contra quién competís, por mercado
A2: Sin precios de la competencia a propósito: cambian seguido y un número viejo acá sería peor que ninguno. Lo que sí es estable es el POSICIONAMIENTO, que es lo que decide si te eligen. Antes de una reunión de venta, mirá el precio del día en su web.
A4: Mercado | B4: Contra quién | C4: Su fuerza | D4: Tu ventaja real | E4: Dónde te ganan
A5: Uruguay | B5: Excel y Google Sheets | C5: Gratis, todos lo saben usar, cero fricción para empezar. | D5: El importador perfila el Excel que ya tienen y sugiere estructura. No les pedís que abandonen su planilla el día uno. | E5: Nada le gana a 'ya lo tengo y es gratis'. La venta es contra la inercia, no contra un producto.
A6: Uruguay | B6: Consultoras locales de PMO | C6: Relación personal, presencia, factura local, hablan tu idioma. | D6: Precio por debajo de una hora de consultoría, y el producto queda corriendo cuando la consultoría termina. | E6: Confianza y respaldo. Un gerente le compra a alguien que puede ir a la oficina.
A7: Uruguay | B7: Odoo / ERPs con módulo de proyectos | C7: Ya instalados en la empresa; el módulo 'viene incluido'. | D7: Salud de portafolio en 6 dimensiones y grafo de bloqueos: eso un módulo de proyectos de ERP no lo hace. | E7: Si ya pagaron el ERP, sumar un módulo es una decisión y comprarte a vos son tres.
A8: LATAM | B8: Monday, Asana, ClickUp, Trello | C8: Marca, marketing enorme, integraciones con todo, apps móviles maduras. | D8: Precio en dólares por instalación, no por asiento. Corre local: el dato no sale de la empresa. Trilingüe de fábrica. | E8: Todo lo demás: app móvil, ecosistema, soporte 24/7, gente que ya sabe usarlos.
A9: LATAM | B9: Jira / Atlassian | C9: Estándar de facto en equipos de software. | D9: No apuntás a equipos de software: apuntás a portafolios de proyectos con gobernanza, PMBOK y dependencias. Es otro comprador. | E9: Si el comprador es un equipo técnico, Jira ya ganó antes de que entres.
A10: Mundo | B10: Smartsheet, Wrike, MS Project, Planview | C10: Venta enterprise, cumplimiento, certificaciones, integradores. | D10: Instalación en la PC del cliente sin enviar datos a la nube ajena — argumento fuerte donde el dato es sensible. | E10: Sin SOC 2 ni ISO 27001 no entrás a una compra corporativa grande, por más que el producto sea bueno.
A11: Mundo | B11: Notion, Obsidian y armados caseros | C11: Flexibles, baratos, comunidad enorme. | D11: El motor de reglas calcula salud y prioridad; una plantilla de Notion no calcula nada, sólo ordena. | E11: Flexibilidad. Se adaptan a cualquier flujo; vos imponés uno.
A13: Lo que este cuadro dice si se lee entero: no tenés una ventaja de producto que un competidor grande no pueda copiar en un trimestre. Tenés dos ventajas de POSICIÓN —corre local sin mandar datos afuera, y el precio no es por asiento— y una de mercado: nadie grande le vende en serio a una PyME uruguaya de 10 personas. Eso es un nicho defendible, no un mercado grande. Está bien: un nicho defendible con 50 clientes pagos es un negocio.

Sheet Palancas
A1: Qué mueve más la aguja: el precio o vender más
A2: LTV = lo que deja un cliente en toda su vida = margen mensual ÷ churn. Es la fórmula estándar y acá está viva: cambiá los supuestos y esto se mueve. Compará las filas entre sí, no mires el número absoluto.
A4: Escenario | B4: Precio USD/mes | C4: Churn mensual | D4: LTV por cliente | E4: vs. hoy | F4: Lectura
A5: HOY | B5: =Supuestos!$B$6 | C5: =Supuestos!$B$13 | D5: =(B5*(1-Supuestos!$B$15)-Supuestos!$B$16)/C5 | F5: El punto de partida.
A6: Precio ×2 (USD 19) | B6: 19 | C6: =Supuestos!$B$13 | D6: =(B6*(1-Supuestos!$B$15)-Supuestos!$B$16)/C6 | E6: =D6/$D$5 | F6: Duplicar el precio duplica el LTV sin vender un cliente más. Es la palanca más barata que tenés: no requiere ads, ni tiempo, ni código.
A7: Precio ×3 (USD 29) | B7: 29 | C7: =Supuestos!$B$13 | D7: =(B7*(1-Supuestos!$B$15)-Supuestos!$B$16)/C7 | E7: =D7/$D$5 | F7: USD 29/mes por una empresa entera sigue estando MUY por debajo de Monday o Asana, que cobran por persona.
A8: Churn a la mitad (2,5%) | B8: =Supuestos!$B$6 | C8: 0.025 | D8: =(B8*(1-Supuestos!$B$15)-Supuestos!$B$16)/C8 | E8: =D8/$D$5 | F8: Que el cliente se quede el doble de tiempo también duplica el LTV. Más difícil que subir el precio, pero se sostiene solo.
A9: Precio ×3 y churn a la mitad | B9: 29 | C9: 0.025 | D9: =(B9*(1-Supuestos!$B$15)-Supuestos!$B$16)/C9 | E9: =D9/$D$5 | F9: Las dos juntas se multiplican, no se suman.
A11: La conclusión incómoda: con los supuestos de la hoja Supuestos, a 24 meses y sin ads quedan poco más de USD 2.000 acumulados. El cuello de botella no es el producto ni el marketing — es el precio. USD 9/mes por una instalación completa es lo que cobra una app de teléfono, no un software de gestión de portafolios que le vendés a una empresa con PMBOK, grafo de dependencias y conectores de BI. Antes de gastar un dólar en ads, probá cobrar tres veces más: si con USD 29 no te compran, con USD 9 tampoco te iban a comprar por mucho tiempo.

Sheet Calificación
A1: Calificación por etapa — con la evidencia de cada nota
A2: Cada nota sale de algo verificado en el código o medido corriendo el programa, no de una impresión. Donde no se pudo verificar, dice que no se pudo.
A4: Etapa | B4: Nota | C4: En qué se apoya | D4: Qué la subiría
A5: Código y mantenibilidad | B5: 8 | C5: 857 tests que corren en CI con ruff; separación motor/UI/API real (el motor se importa sin Streamlit); los comentarios explican POR QUÉ, no qué. Varios tests documentan el bug que los originó. | D5: Cobertura medida (hoy no hay número). Type hints completos en el motor.
A6: Seguridad | B6: 7 | C6: Firma asimétrica Ed25519 (antes era HMAC con secreto que el propio cliente se generaba: cualquiera se emitía licencia enterprise); pago verificado contra MercadoPago y no contra el query string; plan validado en la emisión; canje idempotente; rate limiting; CORS cerrado; comparaciones timing-safe; fuentes compiladas a .pyd en el instalador. | D6: Repo en privado (hoy es público con los .exe adentro). Rotar la clave —ya automatizado— y que /api/estado-licencias diga ok:true.
A7: Funcionalidad | B7: 7 | C7: Motor de reglas completo (salud 6D, dependencias, backlog, PMBOK); tres demos que cargan sin error (sintética, portafolio UK, ClinicalTrials); API de BI + conectores Power BI/Tableau/Fabric + servidor MCP. | D7: Probarlo en una PC con Windows de verdad. Hoy los instaladores se compilan en CI y nadie los ejecutó.
A8: Diseño de interfaz | B8: 6 | C8: Material Symbols nativos con la fuente embebida (funciona sin internet), trilingüe ES/EN/PT con test de paridad, semáforos RAG consistentes. | D8: Es Streamlit: nunca va a verse como un producto a medida. Subir de acá exige otra capa de UI, que es un proyecto en sí.
A9: Web / landing | B9: 7 | C9: Trilingüe, CSP estricta y headers de seguridad completos, sin build ni dependencias. | D9: El botón de descarga responde 503: falta BLOB_READ_WRITE_TOKEN. Es lo primero que ve un interesado.
A10: Cobro y licencias | B10: 6 | C10: La cadena está entera y probada cruzando lenguajes: Node emite como Vercel, Python verifica como la PC del cliente. Medido con servidores corriendo: 402 antes de pagar, 200 después. | D10: Falta MVPM_LICENSE_PRIVATE_KEY en Vercel — hoy quien pague recibe un 500. Ya hay un workflow que lo resuelve con un botón. Y falta una compra real de punta a punta.
A11: Rentabilidad realizada | B11: 2 | C11: Cero ventas. No es una opinión sobre el potencial: es que el circuito de cobro nunca se completó una vez. | D11: Una venta real. Con eso esta nota se mueve más que con seis meses de desarrollo.
A12: GENERAL | B12: 6.5 | C12: Un producto con ingeniería bastante por encima de su madurez comercial. El código está mejor cuidado que el de mucho software que ya factura; lo que falta no es técnico, es haber vendido una vez. | D12: Cargar la clave, publicar el instalador, hacer una compra de prueba con tu propia tarjeta y mirar /api/metricas.
